goodreads_export/__init__.py
goodreads_export/author_file.py
goodreads_export/authored_file.py
goodreads_export/book_file.py
goodreads_export/clean_file_name.py
goodreads_export/data_file.py
goodreads_export/goodreads_book.py
goodreads_export/library.py
goodreads_export/log.py
goodreads_export/main.py
goodreads_export/series_file.py
goodreads_export/stat.py
goodreads_export/template_metadata.py
goodreads_export/templates.py
goodreads_export/version.py
goodreads_export-1.10.0.data/data/LICENSE.txt
goodreads_export-1.10.0.dist-info/licenses/LICENSE.txt
goodreads_export-1.10.0.dist-info/METADATA
goodreads_export-1.10.0.dist-info/WHEEL
goodreads_export-1.10.0.dist-info/entry_points.txt
goodreads_export-1.10.0.dist-info/top_level.txt
goodreads_export-1.10.0.dist-info/zip-safe
goodreads_export-1.10.0.dist-info/RECORD
