Metadata-Version: 2.4
Name: goodreads-export
Version: 1.10.0
Summary: Convert goodreads books to markdown files, for example for Obsidian.
Home-page: https://andgineer.github.io/goodreads-export/en/
Author: Andrey Sorokin
Author-email: andrey@sorokin.engineer
Keywords: goodreads book markdown obsidian
Classifier: Programming Language :: Python :: 3
Classifier: License :: OSI Approved :: MIT License
Classifier: Operating System :: OS Independent
Requires-Python: >=3.9
License-File: LICENSE.txt
Requires-Dist: pandas
Requires-Dist: requests
Requires-Dist: markdownify
Requires-Dist: click
Requires-Dist: rich-click
Requires-Dist: tqdm
Requires-Dist: Jinja2
Requires-Dist: platformdirs
Dynamic: author
Dynamic: author-email
Dynamic: classifier
Dynamic: description
Dynamic: description-content-type
Dynamic: home-page
Dynamic: keywords
Dynamic: license-file
Dynamic: requires-dist
Dynamic: requires-python
Dynamic: summary
